{"nodes": [{"id": "packages_openclaw_plugin_src_core_nocturnal_export_ts", "label": "nocturnal-export.ts", "file_type": "code", "source_file": "packages\\openclaw-plugin\\src\\core\\nocturnal-export.ts", "source_location": "L1"}, {"id": "nocturnal_export_computedatasetfingerprint", "label": "computeDatasetFingerprint()", "file_type": "code", "source_file": "packages\\openclaw-plugin\\src\\core\\nocturnal-export.ts", "source_location": "L147"}, {"id": "nocturnal_export_serializeorposample", "label": "serializeORPOSample()", "file_type": "code", "source_file": "packages\\openclaw-plugin\\src\\core\\nocturnal-export.ts", "source_location": "L163"}, {"id": "nocturnal_export_buildevidencesummary", "label": "buildEvidenceSummary()", "file_type": "code", "source_file": "packages\\openclaw-plugin\\src\\core\\nocturnal-export.ts", "source_location": "L198"}, {"id": "nocturnal_export_buildevidenceboundedrejected", "label": "buildEvidenceBoundedRejected()", "file_type": "code", "source_file": "packages\\openclaw-plugin\\src\\core\\nocturnal-export.ts", "source_location": "L230"}, {"id": "nocturnal_export_buildevidenceboundedrationale", "label": "buildEvidenceBoundedRationale()", "file_type": "code", "source_file": "packages\\openclaw-plugin\\src\\core\\nocturnal-export.ts", "source_location": "L256"}, {"id": "nocturnal_export_exportorposamples", "label": "exportORPOSamples()", "file_type": "code", "source_file": "packages\\openclaw-plugin\\src\\core\\nocturnal-export.ts", "source_location": "L282"}, {"id": "nocturnal_export_verifyexportintegrity", "label": "verifyExportIntegrity()", "file_type": "code", "source_file": "packages\\openclaw-plugin\\src\\core\\nocturnal-export.ts", "source_location": "L420"}, {"id": "nocturnal_export_listexports", "label": "listExports()", "file_type": "code", "source_file": "packages\\openclaw-plugin\\src\\core\\nocturnal-export.ts", "source_location": "L450"}, {"id": "nocturnal_export_getexportmanifest", "label": "getExportManifest()", "file_type": "code", "source_file": "packages\\openclaw-plugin\\src\\core\\nocturnal-export.ts", "source_location": "L483"}], "edges": [{"source": "packages_openclaw_plugin_src_core_nocturnal_export_ts", "target": "fs", "relation": "imports_from", "confidence": "EXTRACTED", "source_file": "packages\\openclaw-plugin\\src\\core\\nocturnal-export.ts", "source_location": "L47", "weight": 1.0}, {"source": "packages_openclaw_plugin_src_core_nocturnal_export_ts", "target": "path", "relation": "imports_from", "confidence": "EXTRACTED", "source_file": "packages\\openclaw-plugin\\src\\core\\nocturnal-export.ts", "source_location": "L48", "weight": 1.0}, {"source": "packages_openclaw_plugin_src_core_nocturnal_export_ts", "target": "crypto", "relation": "imports_from", "confidence": "EXTRACTED", "source_file": "packages\\openclaw-plugin\\src\\core\\nocturnal-export.ts", "source_location": "L49", "weight": 1.0}, {"source": "packages_openclaw_plugin_src_core_nocturnal_export_ts", "target": "packages_openclaw_plugin_src_core_utils_io_ts", "relation": "imports_from", "confidence": "EXTRACTED", "source_file": "packages\\openclaw-plugin\\src\\core\\nocturnal-export.ts", "source_location": "L50", "weight": 1.0}, {"source": "packages_openclaw_plugin_src_core_nocturnal_export_ts", "target": "packages_openclaw_plugin_src_core_nocturnal_dataset_ts", "relation": "imports_from", "confidence": "EXTRACTED", "source_file": "packages\\openclaw-plugin\\src\\core\\nocturnal-export.ts", "source_location": "L51", "weight": 1.0}, {"source": "packages_openclaw_plugin_src_core_nocturnal_export_ts", "target": "packages_openclaw_plugin_src_core_nocturnal_artifact_lineage_ts", "relation": "imports_from", "confidence": "EXTRACTED", "source_file": "packages\\openclaw-plugin\\src\\core\\nocturnal-export.ts", "source_location": "L56", "weight": 1.0}, {"source": "packages_openclaw_plugin_src_core_nocturnal_export_ts", "target": "packages_openclaw_plugin_src_core_nocturnal_paths_ts", "relation": "imports_from", "confidence": "EXTRACTED", "source_file": "packages\\openclaw-plugin\\src\\core\\nocturnal-export.ts", "source_location": "L60", "weight": 1.0}, {"source": "packages_openclaw_plugin_src_core_nocturnal_export_ts", "target": "nocturnal_export_computedatasetfingerprint", "relation": "contains", "confidence": "EXTRACTED", "source_file": "packages\\openclaw-plugin\\src\\core\\nocturnal-export.ts", "source_location": "L147", "weight": 1.0}, {"source": "packages_openclaw_plugin_src_core_nocturnal_export_ts", "target": "nocturnal_export_serializeorposample", "relation": "contains", "confidence": "EXTRACTED", "source_file": "packages\\openclaw-plugin\\src\\core\\nocturnal-export.ts", "source_location": "L163", "weight": 1.0}, {"source": "packages_openclaw_plugin_src_core_nocturnal_export_ts", "target": "nocturnal_export_buildevidencesummary", "relation": "contains", "confidence": "EXTRACTED", "source_file": "packages\\openclaw-plugin\\src\\core\\nocturnal-export.ts", "source_location": "L198", "weight": 1.0}, {"source": "packages_openclaw_plugin_src_core_nocturnal_export_ts", "target": "nocturnal_export_buildevidenceboundedrejected", "relation": "contains", "confidence": "EXTRACTED", "source_file": "packages\\openclaw-plugin\\src\\core\\nocturnal-export.ts", "source_location": "L230", "weight": 1.0}, {"source": "packages_openclaw_plugin_src_core_nocturnal_export_ts", "target": "nocturnal_export_buildevidenceboundedrationale", "relation": "contains", "confidence": "EXTRACTED", "source_file": "packages\\openclaw-plugin\\src\\core\\nocturnal-export.ts", "source_location": "L256", "weight": 1.0}, {"source": "packages_openclaw_plugin_src_core_nocturnal_export_ts", "target": "nocturnal_export_exportorposamples", "relation": "contains", "confidence": "EXTRACTED", "source_file": "packages\\openclaw-plugin\\src\\core\\nocturnal-export.ts", "source_location": "L282", "weight": 1.0}, {"source": "packages_openclaw_plugin_src_core_nocturnal_export_ts", "target": "nocturnal_export_verifyexportintegrity", "relation": "contains", "confidence": "EXTRACTED", "source_file": "packages\\openclaw-plugin\\src\\core\\nocturnal-export.ts", "source_location": "L420", "weight": 1.0}, {"source": "packages_openclaw_plugin_src_core_nocturnal_export_ts", "target": "nocturnal_export_listexports", "relation": "contains", "confidence": "EXTRACTED", "source_file": "packages\\openclaw-plugin\\src\\core\\nocturnal-export.ts", "source_location": "L450", "weight": 1.0}, {"source": "packages_openclaw_plugin_src_core_nocturnal_export_ts", "target": "nocturnal_export_getexportmanifest", "relation": "contains", "confidence": "EXTRACTED", "source_file": "packages\\openclaw-plugin\\src\\core\\nocturnal-export.ts", "source_location": "L483", "weight": 1.0}, {"source": "nocturnal_export_serializeorposample", "target": "nocturnal_export_buildevidenceboundedrejected", "relation": "calls", "confidence": "EXTRACTED", "source_file": "packages\\openclaw-plugin\\src\\core\\nocturnal-export.ts", "source_location": "L172", "weight": 1.0}, {"source": "nocturnal_export_serializeorposample", "target": "nocturnal_export_buildevidenceboundedrationale", "relation": "calls", "confidence": "EXTRACTED", "source_file": "packages\\openclaw-plugin\\src\\core\\nocturnal-export.ts", "source_location": "L185", "weight": 1.0}, {"source": "nocturnal_export_exportorposamples", "target": "nocturnal_export_buildevidencesummary", "relation": "calls", "confidence": "EXTRACTED", "source_file": "packages\\openclaw-plugin\\src\\core\\nocturnal-export.ts", "source_location": "L360", "weight": 1.0}, {"source": "nocturnal_export_exportorposamples", "target": "nocturnal_export_serializeorposample", "relation": "calls", "confidence": "EXTRACTED", "source_file": "packages\\openclaw-plugin\\src\\core\\nocturnal-export.ts", "source_location": "L363", "weight": 1.0}, {"source": "nocturnal_export_exportorposamples", "target": "nocturnal_export_computedatasetfingerprint", "relation": "calls", "confidence": "EXTRACTED", "source_file": "packages\\openclaw-plugin\\src\\core\\nocturnal-export.ts", "source_location": "L376", "weight": 1.0}, {"source": "nocturnal_export_verifyexportintegrity", "target": "nocturnal_export_computedatasetfingerprint", "relation": "calls", "confidence": "EXTRACTED", "source_file": "packages\\openclaw-plugin\\src\\core\\nocturnal-export.ts", "source_location": "L433", "weight": 1.0}], "raw_calls": [{"caller_nid": "nocturnal_export_computedatasetfingerprint", "callee": "sort", "source_file": "packages\\openclaw-plugin\\src\\core\\nocturnal-export.ts", "source_location": "L148"}, {"caller_nid": "nocturnal_export_computedatasetfingerprint", "callee": "join", "source_file": "packages\\openclaw-plugin\\src\\core\\nocturnal-export.ts", "source_location": "L149"}, {"caller_nid": "nocturnal_export_computedatasetfingerprint", "callee": "digest", "source_file": "packages\\openclaw-plugin\\src\\core\\nocturnal-export.ts", "source_location": "L150"}, {"caller_nid": "nocturnal_export_computedatasetfingerprint", "callee": "update", "source_file": "packages\\openclaw-plugin\\src\\core\\nocturnal-export.ts", "source_location": "L150"}, {"caller_nid": "nocturnal_export_computedatasetfingerprint", "callee": "createHash", "source_file": "packages\\openclaw-plugin\\src\\core\\nocturnal-export.ts", "source_location": "L150"}, {"caller_nid": "nocturnal_export_serializeorposample", "callee": "toISOString", "source_file": "packages\\openclaw-plugin\\src\\core\\nocturnal-export.ts", "source_location": "L170"}, {"caller_nid": "nocturnal_export_buildevidenceboundedrejected", "callee": "push", "source_file": "packages\\openclaw-plugin\\src\\core\\nocturnal-export.ts", "source_location": "L240"}, {"caller_nid": "nocturnal_export_buildevidenceboundedrejected", "callee": "push", "source_file": "packages\\openclaw-plugin\\src\\core\\nocturnal-export.ts", "source_location": "L243"}, {"caller_nid": "nocturnal_export_buildevidenceboundedrejected", "callee": "trim", "source_file": "packages\\openclaw-plugin\\src\\core\\nocturnal-export.ts", "source_location": "L250"}, {"caller_nid": "nocturnal_export_buildevidenceboundedrejected", "callee": "join", "source_file": "packages\\openclaw-plugin\\src\\core\\nocturnal-export.ts", "source_location": "L253"}, {"caller_nid": "nocturnal_export_exportorposamples", "callee": "randomUUID", "source_file": "packages\\openclaw-plugin\\src\\core\\nocturnal-export.ts", "source_location": "L287"}, {"caller_nid": "nocturnal_export_exportorposamples", "callee": "toISOString", "source_file": "packages\\openclaw-plugin\\src\\core\\nocturnal-export.ts", "source_location": "L288"}, {"caller_nid": "nocturnal_export_exportorposamples", "callee": "listArtifactLineageRecords", "source_file": "packages\\openclaw-plugin\\src\\core\\nocturnal-export.ts", "source_location": "L289"}, {"caller_nid": "nocturnal_export_exportorposamples", "callee": "listDatasetRecords", "source_file": "packages\\openclaw-plugin\\src\\core\\nocturnal-export.ts", "source_location": "L294"}, {"caller_nid": "nocturnal_export_exportorposamples", "callee": "listDatasetRecords", "source_file": "packages\\openclaw-plugin\\src\\core\\nocturnal-export.ts", "source_location": "L304"}, {"caller_nid": "nocturnal_export_exportorposamples", "callee": "some", "source_file": "packages\\openclaw-plugin\\src\\core\\nocturnal-export.ts", "source_location": "L305"}, {"caller_nid": "nocturnal_export_exportorposamples", "callee": "filter", "source_file": "packages\\openclaw-plugin\\src\\core\\nocturnal-export.ts", "source_location": "L315"}, {"caller_nid": "nocturnal_export_exportorposamples", "callee": "push", "source_file": "packages\\openclaw-plugin\\src\\core\\nocturnal-export.ts", "source_location": "L337"}, {"caller_nid": "nocturnal_export_exportorposamples", "callee": "push", "source_file": "packages\\openclaw-plugin\\src\\core\\nocturnal-export.ts", "source_location": "L343"}, {"caller_nid": "nocturnal_export_exportorposamples", "callee": "readDatasetArtifact", "source_file": "packages\\openclaw-plugin\\src\\core\\nocturnal-export.ts", "source_location": "L352"}, {"caller_nid": "nocturnal_export_exportorposamples", "callee": "push", "source_file": "packages\\openclaw-plugin\\src\\core\\nocturnal-export.ts", "source_location": "L354"}, {"caller_nid": "nocturnal_export_exportorposamples", "callee": "find", "source_file": "packages\\openclaw-plugin\\src\\core\\nocturnal-export.ts", "source_location": "L359"}, {"caller_nid": "nocturnal_export_exportorposamples", "callee": "push", "source_file": "packages\\openclaw-plugin\\src\\core\\nocturnal-export.ts", "source_location": "L363"}, {"caller_nid": "nocturnal_export_exportorposamples", "callee": "map", "source_file": "packages\\openclaw-plugin\\src\\core\\nocturnal-export.ts", "source_location": "L377"}, {"caller_nid": "nocturnal_export_exportorposamples", "callee": "exportsDir", "source_file": "packages\\openclaw-plugin\\src\\core\\nocturnal-export.ts", "source_location": "L386"}, {"caller_nid": "nocturnal_export_exportorposamples", "callee": "join", "source_file": "packages\\openclaw-plugin\\src\\core\\nocturnal-export.ts", "source_location": "L387"}, {"caller_nid": "nocturnal_export_exportorposamples", "callee": "join", "source_file": "packages\\openclaw-plugin\\src\\core\\nocturnal-export.ts", "source_location": "L388"}, {"caller_nid": "nocturnal_export_exportorposamples", "callee": "map", "source_file": "packages\\openclaw-plugin\\src\\core\\nocturnal-export.ts", "source_location": "L388"}, {"caller_nid": "nocturnal_export_exportorposamples", "callee": "atomicWriteFileSync", "source_file": "packages\\openclaw-plugin\\src\\core\\nocturnal-export.ts", "source_location": "L389"}, {"caller_nid": "nocturnal_export_exportorposamples", "callee": "join", "source_file": "packages\\openclaw-plugin\\src\\core\\nocturnal-export.ts", "source_location": "L399"}, {"caller_nid": "nocturnal_export_exportorposamples", "callee": "map", "source_file": "packages\\openclaw-plugin\\src\\core\\nocturnal-export.ts", "source_location": "L400"}, {"caller_nid": "nocturnal_export_exportorposamples", "callee": "atomicWriteFileSync", "source_file": "packages\\openclaw-plugin\\src\\core\\nocturnal-export.ts", "source_location": "L408"}, {"caller_nid": "nocturnal_export_exportorposamples", "callee": "stringify", "source_file": "packages\\openclaw-plugin\\src\\core\\nocturnal-export.ts", "source_location": "L408"}, {"caller_nid": "nocturnal_export_verifyexportintegrity", "callee": "exportsDir", "source_file": "packages\\openclaw-plugin\\src\\core\\nocturnal-export.ts", "source_location": "L424"}, {"caller_nid": "nocturnal_export_verifyexportintegrity", "callee": "join", "source_file": "packages\\openclaw-plugin\\src\\core\\nocturnal-export.ts", "source_location": "L425"}, {"caller_nid": "nocturnal_export_verifyexportintegrity", "callee": "existsSync", "source_file": "packages\\openclaw-plugin\\src\\core\\nocturnal-export.ts", "source_location": "L427"}, {"caller_nid": "nocturnal_export_verifyexportintegrity", "callee": "parse", "source_file": "packages\\openclaw-plugin\\src\\core\\nocturnal-export.ts", "source_location": "L432"}, {"caller_nid": "nocturnal_export_verifyexportintegrity", "callee": "readFileSync", "source_file": "packages\\openclaw-plugin\\src\\core\\nocturnal-export.ts", "source_location": "L432"}, {"caller_nid": "nocturnal_export_verifyexportintegrity", "callee": "map", "source_file": "packages\\openclaw-plugin\\src\\core\\nocturnal-export.ts", "source_location": "L434"}, {"caller_nid": "nocturnal_export_listexports", "callee": "exportsDir", "source_file": "packages\\openclaw-plugin\\src\\core\\nocturnal-export.ts", "source_location": "L451"}, {"caller_nid": "nocturnal_export_listexports", "callee": "existsSync", "source_file": "packages\\openclaw-plugin\\src\\core\\nocturnal-export.ts", "source_location": "L452"}, {"caller_nid": "nocturnal_export_listexports", "callee": "readdirSync", "source_file": "packages\\openclaw-plugin\\src\\core\\nocturnal-export.ts", "source_location": "L457"}, {"caller_nid": "nocturnal_export_listexports", "callee": "endsWith", "source_file": "packages\\openclaw-plugin\\src\\core\\nocturnal-export.ts", "source_location": "L461"}, {"caller_nid": "nocturnal_export_listexports", "callee": "parse", "source_file": "packages\\openclaw-plugin\\src\\core\\nocturnal-export.ts", "source_location": "L463"}, {"caller_nid": "nocturnal_export_listexports", "callee": "readFileSync", "source_file": "packages\\openclaw-plugin\\src\\core\\nocturnal-export.ts", "source_location": "L464"}, {"caller_nid": "nocturnal_export_listexports", "callee": "join", "source_file": "packages\\openclaw-plugin\\src\\core\\nocturnal-export.ts", "source_location": "L464"}, {"caller_nid": "nocturnal_export_listexports", "callee": "push", "source_file": "packages\\openclaw-plugin\\src\\core\\nocturnal-export.ts", "source_location": "L466"}, {"caller_nid": "nocturnal_export_listexports", "callee": "sort", "source_file": "packages\\openclaw-plugin\\src\\core\\nocturnal-export.ts", "source_location": "L472"}, {"caller_nid": "nocturnal_export_getexportmanifest", "callee": "exportsDir", "source_file": "packages\\openclaw-plugin\\src\\core\\nocturnal-export.ts", "source_location": "L487"}, {"caller_nid": "nocturnal_export_getexportmanifest", "callee": "join", "source_file": "packages\\openclaw-plugin\\src\\core\\nocturnal-export.ts", "source_location": "L488"}, {"caller_nid": "nocturnal_export_getexportmanifest", "callee": "existsSync", "source_file": "packages\\openclaw-plugin\\src\\core\\nocturnal-export.ts", "source_location": "L490"}, {"caller_nid": "nocturnal_export_getexportmanifest", "callee": "parse", "source_file": "packages\\openclaw-plugin\\src\\core\\nocturnal-export.ts", "source_location": "L495"}, {"caller_nid": "nocturnal_export_getexportmanifest", "callee": "readFileSync", "source_file": "packages\\openclaw-plugin\\src\\core\\nocturnal-export.ts", "source_location": "L495"}]}