{"nodes": [{"id": "packages_openclaw_plugin_src_utils_node_vm_polyfill_ts", "label": "node-vm-polyfill.ts", "file_type": "code", "source_file": "packages\\openclaw-plugin\\src\\utils\\node-vm-polyfill.ts", "source_location": "L1"}], "edges": [{"source": "packages_openclaw_plugin_src_utils_node_vm_polyfill_ts", "target": "node_vm", "relation": "imports_from", "confidence": "EXTRACTED", "source_file": "packages\\openclaw-plugin\\src\\utils\\node-vm-polyfill.ts", "source_location": "L9", "weight": 1.0}], "raw_calls": []}